wowspy
