Metadata-Version: 1.1
Name: wowspy
Version: 1.2.3
Summary: A Python World of Warships API wrapper
Home-page: https://github.com/MaT1g3R/Warships.py
Author: MaT1g3R
Author-email: mat1g3r@gmail.com
License: MIT
Platform: UNKNOWN
Classifier: License :: OSI Approved :: MIT License
Classifier: Intended Audience :: Developers
Classifier: Natural Language :: English
Classifier: Operating System :: OS Independent
Classifier: Programming Language :: Python :: 3.5
Classifier: Programming Language :: Python :: 3.6
Classifier: Topic :: Internet
Classifier: Topic :: Software Development :: Libraries
Classifier: Topic :: Software Development :: Libraries :: Python Modules
Classifier: Topic :: Utilities
